{
  "cataloge": [
    {
        "img": "https://images.unsplash.com/photo-1506424482693-1f123321fa53?ixlib=rb-4.0.3&ixid=M3wxMjA3fDB8MHxwaG90by1wYWdlfHx8fGVufDB8fHx8fA%3D%3D&auto=format&fit=crop&w=1703&q=80",
        "alt": "moto",
        "dataModal": "c1",
        "title": "Катание на кроссовом мотоцикле",
        "oldPrice": "4 900",
        "price": "4 001",
        "id": "c1",
        "descr": "card1 Lorem ipsum dolor, sit amet consectetur adipisicing elit. Minus, ullam corrupti libero perferendis culpa qui blanditiis at cupiditate id totam dolorem asperiores, illum labore fuga optio dolores! Tempore, cumque iusto. Lorem ipsum dolor sit amet consectetur adipisicing elit. Iusto cumque, aspernatur dicta corrupti aliquam officiis neque tempore minima consequuntur possimus blanditiis, eum eligendi numquam error, optio obcaecati? Rem, vitae maiores! Lorem ipsum dolor, sit amet consectetur adipisicing elit. Minus, ullam corrupti libero perferendis culpa qui blanditiis at cupiditate id totam dolorem asperiores, illum labore fuga optio dolores! Tempore, cumque iusto. Lorem ipsum dolor sit amet consectetur adipisicing elit. Iusto cumque, aspernatur dicta corrupti aliquam officiis neque tempore minima consequuntur possimus blanditiis, eum eligendi numquam error, optio obcaecati? Rem, vitae maiores!"
    },
    {
        "img": "https://images.unsplash.com/photo-1506424482693-1f123321fa53?ixlib=rb-4.0.3&ixid=M3wxMjA3fDB8MHxwaG90by1wYWdlfHx8fGVufDB8fHx8fA%3D%3D&auto=format&fit=crop&w=1703&q=80",
        "alt": "moto",
        "dataModal": "c2",
        "title": "Катание на кроссовом мотоцикле",
        "oldPrice": "4 900",
        "price": "4 002",
        "id": "c2",
        "descr": "card2"
    },
    {
        "img": "https://images.unsplash.com/photo-1506424482693-1f123321fa53?ixlib=rb-4.0.3&ixid=M3wxMjA3fDB8MHxwaG90by1wYWdlfHx8fGVufDB8fHx8fA%3D%3D&auto=format&fit=crop&w=1703&q=80",
        "alt": "moto",
        "dataModal": "c3",
        "title": "Катание на кроссовом мотоцикле",
        "oldPrice": "4 900",
        "price": "4 003",
        "id": "c3",
        "descr": "card3"
    },
    {
        "img": "https://images.unsplash.com/photo-1506424482693-1f123321fa53?ixlib=rb-4.0.3&ixid=M3wxMjA3fDB8MHxwaG90by1wYWdlfHx8fGVufDB8fHx8fA%3D%3D&auto=format&fit=crop&w=1703&q=80",
        "alt": "moto",
        "dataModal": "c4",
        "title": "Катание на кроссовом мотоцикле",
        "oldPrice": "4 900",
        "price": "4 004",
        "id": "c4",
        "descr": "card4"
    },
    {
        "img": "https://images.unsplash.com/photo-1506424482693-1f123321fa53?ixlib=rb-4.0.3&ixid=M3wxMjA3fDB8MHxwaG90by1wYWdlfHx8fGVufDB8fHx8fA%3D%3D&auto=format&fit=crop&w=1703&q=80",
        "alt": "moto",
        "dataModal": "c5",
        "title": "Катание на кроссовом мотоцикле",
        "oldPrice": "4 900",
        "price": "4 005",
        "id": "c5",
        "descr": "card5"
    },
    {
        "img": "https://images.unsplash.com/photo-1506424482693-1f123321fa53?ixlib=rb-4.0.3&ixid=M3wxMjA3fDB8MHxwaG90by1wYWdlfHx8fGVufDB8fHx8fA%3D%3D&auto=format&fit=crop&w=1703&q=80",
        "alt": "moto",
        "dataModal": "c6",
        "title": "Катание на кроссовом мотоцикле",
        "oldPrice": "4 900",
        "price": "4 006",
        "id": "c6",
        "descr": "card6"
    },
    {
        "img": "https://images.unsplash.com/photo-1506424482693-1f123321fa53?ixlib=rb-4.0.3&ixid=M3wxMjA3fDB8MHxwaG90by1wYWdlfHx8fGVufDB8fHx8fA%3D%3D&auto=format&fit=crop&w=1703&q=80",
        "alt": "moto",
        "dataModal": "c7",
        "title": "Катание на кроссовом мотоцикле",
        "oldPrice": "4 900",
        "price": "4 007",
        "id": "c7",
        "descr": "card7"
    },
    {
        "img": "https://images.unsplash.com/photo-1506424482693-1f123321fa53?ixlib=rb-4.0.3&ixid=M3wxMjA3fDB8MHxwaG90by1wYWdlfHx8fGVufDB8fHx8fA%3D%3D&auto=format&fit=crop&w=1703&q=80",
        "alt": "moto",
        "dataModal": "c8",
        "title": "Катание на кроссовом мотоцикле",
        "oldPrice": "4 900",
        "price": "4 008",
        "id": "c8",
        "descr": "card8"
    },
    {
        "img": "https://images.unsplash.com/photo-1506424482693-1f123321fa53?ixlib=rb-4.0.3&ixid=M3wxMjA3fDB8MHxwaG90by1wYWdlfHx8fGVufDB8fHx8fA%3D%3D&auto=format&fit=crop&w=1703&q=80",
        "alt": "moto",
        "dataModal": "c9",
        "title": "Катание на кроссовом мотоцикле",
        "oldPrice": "4 900",
        "price": "4 009",
        "id": "c9",
        "descr": "card9"
    },
    {
        "img": "https://images.unsplash.com/photo-1506424482693-1f123321fa53?ixlib=rb-4.0.3&ixid=M3wxMjA3fDB8MHxwaG90by1wYWdlfHx8fGVufDB8fHx8fA%3D%3D&auto=format&fit=crop&w=1703&q=80",
        "alt": "moto",
        "dataModal": "c10",
        "title": "Катание на кроссовом мотоцикле",
        "oldPrice": "4 900",
        "price": "4 010",
        "id": "c10",
        "descr": "card10"
    }
  ],
  "boxes": [
    {
        "img": "images/pack-img.png",
        "alt": "emotion",
        "dataModal": "b1",
        "title": "В мире эмоций",
        "oldPrice": "6 900",
        "price": "5 001",
        "id": "b1",
        "descr": "card1 Lorem ipsum dolor, sit amet consectetur adipisicing elit. Minus, ullam corrupti libero perferendis culpa qui blanditiis at cupiditate id totam dolorem asperiores, illum labore fuga optio dolores! Tempore, cumque iusto. Lorem ipsum dolor sit amet consectetur adipisicing elit. Iusto cumque, aspernatur dicta corrupti aliquam officiis neque tempore minima consequuntur possimus blanditiis, eum eligendi numquam error, optio obcaecati? Rem, vitae maiores! Lorem ipsum dolor, sit amet consectetur adipisicing elit. Minus, ullam corrupti libero perferendis culpa qui blanditiis at cupiditate id totam dolorem asperiores, illum labore fuga optio dolores! Tempore, cumque iusto. Lorem ipsum dolor sit amet consectetur adipisicing elit. Iusto cumque, aspernatur dicta corrupti aliquam officiis neque tempore minima consequuntur possimus blanditiis, eum eligendi numquam error, optio obcaecati? Rem, vitae maiores!"
    },
    {
        "img": "images/pack-img.png",
        "alt": "emotion",
        "dataModal": "b2",
        "title": "В мире эмоций",
        "oldPrice": "6 900",
        "price": "5 002",
        "id": "b2",
        "descr": "card2"
    },
    {
        "img": "images/pack-img.png",
        "alt": "emotion",
        "dataModal": "b3",
        "title": "В мире эмоций",
        "oldPrice": "6 900",
        "price": "5 003",
        "id": "b3",
        "descr": "card3"
    },
    {
        "img": "images/pack-img.png",
        "alt": "emotion",
        "dataModal": "b4",
        "title": "В мире эмоций",
        "oldPrice": "6 900",
        "price": "5 004",
        "id": "b4",
        "descr": "card4"
    },
    {
        "img": "images/pack-img.png",
        "alt": "emotion",
        "dataModal": "b5",
        "title": "В мире эмоций",
        "oldPrice": "6 900",
        "price": "5 005",
        "id": "b5",
        "descr": "card5"
    },
    {
        "img": "images/pack-img.png",
        "alt": "emotion",
        "dataModal": "b6",
        "title": "В мире эмоций",
        "oldPrice": "6 900",
        "price": "5 006",
        "id": "b6",
        "descr": "card6"
    },
    {
        "img": "images/pack-img.png",
        "alt": "emotion",
        "dataModal": "b7",
        "title": "В мире эмоций",
        "oldPrice": "6 900",
        "price": "5 007",
        "id": "b7",
        "descr": "card7"
    },
    {
        "img": "images/pack-img.png",
        "alt": "emotion",
        "dataModal": "b8",
        "title": "В мире эмоций",
        "oldPrice": "6 900",
        "price": "5 008",
        "id": "b8",
        "descr": "card8"
    },
    {
        "img": "images/pack-img.png",
        "alt": "emotion",
        "dataModal": "b9",
        "title": "В мире эмоций",
        "oldPrice": "6 900",
        "price": "5 009",
        "id": "b9",
        "descr": "card9"
    },
    {
        "img": "images/pack-img.png",
        "alt": "emotion",
        "dataModal": "b10",
        "title": "В мире эмоций",
        "oldPrice": "6 900",
        "price": "5 010",
        "id": "b10",
        "descr": "card10"
    }
  ],
  "activate": [
    {
      "name": "qq",
      "phone": "+7 (111) 122-22-22",
      "email": "asdfasf@mail.ru",
      "code": "018868",
      "id": 1
    },
    {
      "name": "trav",
      "phone": "+7 (333) 333-33-33",
      "email": "asdfasf@mail.ru",
      "code": "12345",
      "id": 2
    }
  ],
  "callback": [
    {
      "name": "sdfsdf",
      "phone": "+7 (911) 168-33-42",
      "email": "asdfasf@mail.ru",
      "id": 1
    },
    {
      "name": "Food",
      "phone": "+7 (111) 111-11-11",
      "email": "asdfasf@mail.ru",
      "id": 2
    }
  ]
}